route0x/__init__.py
route0x/route_builder/__init__.py
route0x/route_builder/config.json
route0x/route_builder/losses.py
route0x/route_builder/outlier_detector.py
route0x/route_builder/route_builder.py
route0x/route_builder/unified_llm_caller.py
route0x/route_builder/vector_db.py
route0x/route_builder/data/outliers.csv
route0x/route_builder/data/outliers_v1.csv
route0x/route_finder/__init__.py
route0x/route_finder/route_finder.py
route0x/route_finder/vector_db.py
Route0x-0.1.24.dist-info/LICENSE
Route0x-0.1.24.dist-info/METADATA
Route0x-0.1.24.dist-info/WHEEL
Route0x-0.1.24.dist-info/top_level.txt
Route0x-0.1.24.dist-info/RECORD
