Metadata-Version: 2.1
Name: Route0x
Version: 0.1.24
Summary: Low latency, High Accuracy, Custom Query routers.
Classifier: Programming Language :: Python :: 3
Classifier: License :: OSI Approved :: MIT License
Classifier: Operating System :: OS Independent
Requires-Python: >=3.8
License-File: LICENSE
Provides-Extra: build
Requires-Dist: pandas (==2.2.3) ; extra == 'build'
Requires-Dist: datasets (==3.2.0) ; extra == 'build'
Requires-Dist: sentence-transformers (==4.0.1) ; extra == 'build'
Requires-Dist: setfit (==1.0.2) ; extra == 'build'
Requires-Dist: onnx (==1.14.0) ; extra == 'build'
Requires-Dist: onnxruntime (==1.15.1) ; extra == 'build'
Requires-Dist: tqdm (==4.67.1) ; extra == 'build'
Requires-Dist: scikit-learn (==1.6.1) ; extra == 'build'
Requires-Dist: huggingface-hub (==0.23.5) ; extra == 'build'
Requires-Dist: accelerate (==1.5.2) ; extra == 'build'
Requires-Dist: ollama (==0.4.7) ; extra == 'build'
Requires-Dist: matplotlib (==3.10.1) ; extra == 'build'
Requires-Dist: chardet (==5.2.0) ; extra == 'build'
Requires-Dist: openai (==1.57.2) ; extra == 'build'
Requires-Dist: anthropic (==0.49.0) ; extra == 'build'
Requires-Dist: onnxconverter-common (==1.14.0) ; extra == 'build'
Requires-Dist: faiss-cpu (==1.10.0) ; extra == 'build'
Requires-Dist: nlpaug (==1.1.11) ; extra == 'build'
Requires-Dist: kneed (==0.8.5) ; extra == 'build'
Requires-Dist: numpy (==1.25.0) ; extra == 'build'
Provides-Extra: route
Requires-Dist: numpy (==1.24.4) ; extra == 'route'
Requires-Dist: tokenizers (==0.19.1) ; extra == 'route'
Requires-Dist: onnxruntime (==1.15.1) ; extra == 'route'
Requires-Dist: joblib (==1.4.2) ; extra == 'route'
Requires-Dist: faiss-cpu ; extra == 'route'
Requires-Dist: seaborn ; extra == 'route'
